atarigon/__init__.py
atarigon/api.py
atarigon/exceptions.py
atarigon/main.py
atarigon-0.1.1.dist-info/LICENSE
atarigon-0.1.1.dist-info/METADATA
atarigon-0.1.1.dist-info/WHEEL
atarigon-0.1.1.dist-info/entry_points.txt
atarigon-0.1.1.dist-info/RECORD
